count_tokens.py
count_tokens_cli-0.1.0.dist-info/LICENSE
count_tokens_cli-0.1.0.dist-info/METADATA
count_tokens_cli-0.1.0.dist-info/WHEEL
count_tokens_cli-0.1.0.dist-info/entry_points.txt
count_tokens_cli-0.1.0.dist-info/RECORD
