Metadata-Version: 2.1
Name: count-tokens-cli
Version: 0.1.0
Summary: Count tokens in git-tracked files using tiktoken encoding for LLM API cost estimation
Home-page: https://github.com/StGerman/count-tokens
Author: Stas German
Author-email: stas.german@gmail.com
Requires-Python: >=3.11,<4.0
Classifier: Programming Language :: Python :: 3
Classifier: Programming Language :: Python :: 3.11
Classifier: Programming Language :: Python :: 3.12
Requires-Dist: pathspec (>=0.12.0,<0.13.0)
Requires-Dist: tiktoken (>=0.11.0,<0.12.0)
Project-URL: Repository, https://github.com/StGerman/count-tokens
